Metadata-Version: 2.1
Name: django-webpack-custom-loader
Version: 0.7.0
Summary: Transparently use webpack with django
Home-page: https://github.com/vetcove/django-webpack-loader
Author: Vetcove
Author-email: support@vetcove.com
License: UNKNOWN
Download-URL: https://github.com/vetcove/django-webpack-loader/tarball/0.7.0
Keywords: django,webpack,assets
Platform: UNKNOWN
Classifier: Programming Language :: Python :: 3.3
Classifier: Programming Language :: Python :: 3.4
Classifier: Programming Language :: Python :: 3.5
Classifier: Framework :: Django
Classifier: Environment :: Web Environment
Classifier: License :: OSI Approved :: MIT License
